[{"precipType": "rain", "cloudCover": 0.58, "precipTypeSnow": false, "timeHour": "2017-11-22 21", "temperature": 58.49, "dewPoint": 56.85, "location": "Seattle", "num_tweets": 70.0, "windBearing": 138, "sentiment_average": 0.22023049371263662, "apparentTemperature": 58.49, "pressure": 1015.47, "visibility": 10, "precipTypeRain": true, "precipTypeNone": false, "icon": "partly-cloudy-day", "sentiment_percent_positive": 0.6880000000000002, "created_at": {"$date": 1511402402000}, "humidity": 0.94, "windSpeed": 2.17, "time": 1511370000, "precipIntensity": 0.0015, "precipProbability": 0.15}, {"precipType": "rain", "cloudCover": 0.76, "precipTypeSnow": false, "timeHour": "2017-11-22 20", "temperature": 58.09, "dewPoint": 56.66, "location": "Seattle", "num_tweets": 134.0, "windBearing": 127, "sentiment_average": 0.2382373025977271, "apparentTemperature": 58.09, "pressure": 1014.86, "visibility": 10, "precipTypeRain": true, "precipTypeNone": false, "icon": "partly-cloudy-day", "sentiment_percent_positive": 0.7010572139303481, "created_at": {"$date": 1511398804000}, "humidity": 0.95, "windSpeed": 3.33, "time": 1511366400, "precipIntensity": 0.003, "precipProbability": 0.29}, {"precipType": "rain", "cloudCover": 0.71, "precipTypeSnow": false, "timeHour": "2017-11-22 23", "temperature": 59.75, "dewPoint": 57.85, "location": "Seattle", "num_tweets": 114.0, "windBearing": 152, "sentiment_average": 0.2007892363484469, "apparentTemperature": 59.82, "pressure": 1015.43, "visibility": 10, "precipTypeRain": true, "precipTypeNone": false, "icon": "partly-cloudy-day", "sentiment_percent_positive": 0.6710526315789471, "created_at": {"$date": 1511409617000}, "humidity": 0.93, "windSpeed": 3, "time": 1511377200, "precipIntensity": 0.0092, "precipProbability": 0.45}, {"precipType": "rain", "cloudCover": 0.57, "precipTypeSnow": false, "timeHour": "2017-11-22 22", "temperature": 59.07, "dewPoint": 57.39, "location": "Seattle", "num_tweets": 80.0, "windBearing": 162, "sentiment_average": 0.25806425302128433, "apparentTemperature": 59.1, "pressure": 1015.35, "visibility": 10, "precipTypeRain": true, "precipTypeNone": false, "icon": "partly-cloudy-day", "sentiment_percent_positive": 0.7062499999999998, "created_at": {"$date": 1511406005000}, "humidity": 0.94, "windSpeed": 2.46, "time": 1511373600, "precipIntensity": 0.0005, "precipProbability": 0.03}, {"precipType": "rain", "cloudCover": 0.8, "precipTypeSnow": false, "timeHour": "2017-11-23 22", "temperature": 53.37, "dewPoint": 51.59, "location": "Seattle", "num_tweets": 81.0, "windBearing": 206, "sentiment_average": 0.199063830545312, "apparentTemperature": 53.37, "pressure": 1009.87, "visibility": 6.32, "precipTypeRain": true, "precipTypeNone": false, "icon": "partly-cloudy-day", "sentiment_percent_positive": 0.6820987654320988, "created_at": {"$date": 1511492414000}, "humidity": 0.94, "windSpeed": 4.56, "time": 1511460000, "precipIntensity": 0.0237, "precipProbability": 0.78}, {"precipType": "NoPrecip", "cloudCover": 0.41, "precipTypeSnow": false, "timeHour": "2017-11-24 08", "temperature": 46.71, "dewPoint": 41.77, "location": "Seattle", "num_tweets": 14.0, "windBearing": 171, "sentiment_average": 0.39549319727891163, "apparentTemperature": 42.91, "pressure": 1018.53, "visibility": 10, "precipTypeRain": false, "precipTypeNone": true, "icon": "partly-cloudy-day", "sentiment_percent_positive": 0.9285714285714286, "created_at": {"$date": 1511528768000}, "humidity": 0.83, "windSpeed": 7.68, "time": 1511539200, "precipIntensity": 0, "precipProbability": 0}, {"precipType": "rain", "cloudCover": 0.55, "precipTypeSnow": false, "timeHour": "2017-11-24 10", "temperature": 49.31, "dewPoint": 42.07, "location": "Seattle", "num_tweets": 70.0, "windBearing": 175, "sentiment_average": 0.17305456778671072, "apparentTemperature": 46.35, "pressure": 1018.99, "visibility": 10, "precipTypeRain": true, "precipTypeNone": false, "icon": "partly-cloudy-day", "sentiment_percent_positive": 0.5678571428571428, "created_at": {"$date": 1511535613000}, "humidity": 0.76, "windSpeed": 7.02, "time": 1511546400, "precipIntensity": 0.0005, "precipProbability": 0.05}, {"precipType": "rain", "cloudCover": 0.58, "precipTypeSnow": false, "timeHour": "2017-11-23 13", "temperature": 57.56, "dewPoint": 55.8, "location": "Seattle", "num_tweets": 177.0, "windBearing": 197, "sentiment_average": 0.4230085957499226, "apparentTemperature": 57.56, "pressure": 1010.98, "visibility": 6.86, "precipTypeRain": true, "precipTypeNone": false, "icon": "rain", "sentiment_percent_positive": 0.7768361581920901, "created_at": {"$date": 1511460001000}, "humidity": 0.94, "windSpeed": 9.74, "time": 1511427600, "precipIntensity": 0.0512, "precipProbability": 0.81}, {"precipType": "rain", "cloudCover": 0.62, "precipTypeSnow": false, "timeHour": "2017-11-23 00", "temperature": 52.22, "dewPoint": 50.35, "location": "Seattle", "num_tweets": 112.0, "windBearing": 231, "sentiment_average": 0.22720274062907989, "apparentTemperature": 52.22, "pressure": 1010.33, "visibility": 7.08, "precipTypeRain": true, "precipTypeNone": false, "icon": "partly-cloudy-day", "sentiment_percent_positive": 0.7354166666666667, "created_at": {"$date": 1511413235000}, "humidity": 0.93, "windSpeed": 3.32, "time": 1511467200, "precipIntensity": 0.0187, "precipProbability": 0.71}, {"precipType": "rain", "cloudCover": 0.58, "precipTypeSnow": false, "timeHour": "2017-11-23 01", "temperature": 57.56, "dewPoint": 55.8, "location": "Seattle", "num_tweets": 111.0, "windBearing": 197, "sentiment_average": 0.21251520568187243, "apparentTemperature": 57.56, "pressure": 1010.98, "visibility": 6.86, "precipTypeRain": true, "precipTypeNone": false, "icon": "rain", "sentiment_percent_positive": 0.687153387153387, "created_at": {"$date": 1511416820000}, "humidity": 0.94, "windSpeed": 9.74, "time": 1511427600, "precipIntensity": 0.0512, "precipProbability": 0.81}, {"precipType": "rain", "cloudCover": 0.61, "precipTypeSnow": false, "timeHour": "2017-11-23 02", "temperature": 56.89, "dewPoint": 54.97, "location": "Seattle", "num_tweets": 60.0, "windBearing": 191, "sentiment_average": 0.27546210117043424, "apparentTemperature": 56.89, "pressure": 1011.27, "visibility": 7.31, "precipTypeRain": true, "precipTypeNone": false, "icon": "partly-cloudy-night", "sentiment_percent_positive": 0.785, "created_at": {"$date": 1511420403000}, "humidity": 0.93, "windSpeed": 8.58, "time": 1511431200, "precipIntensity": 0.0095, "precipProbability": 0.52}, {"precipType": "rain", "cloudCover": 0.54, "precipTypeSnow": false, "timeHour": "2017-11-23 03", "temperature": 56.42, "dewPoint": 54.41, "location": "Seattle", "num_tweets": 25.0, "windBearing": 188, "sentiment_average": 0.2517204184704184, "apparentTemperature": 56.42, "pressure": 1011.7, "visibility": 7.33, "precipTypeRain": true, "precipTypeNone": false, "icon": "partly-cloudy-night", "sentiment_percent_positive": 0.6829999999999999, "created_at": {"$date": 1511424102000}, "humidity": 0.93, "windSpeed": 8.7, "time": 1511434800, "precipIntensity": 0.0017, "precipProbability": 0.16}, {"precipType": "rain", "cloudCover": 0.29, "precipTypeSnow": false, "timeHour": "2017-11-14 19", "temperature": 46.12, "dewPoint": 41.59, "location": "Seattle", "num_tweets": 85.0, "windBearing": 139, "sentiment_average": 0.3145134750870045, "apparentTemperature": 41.47, "pressure": 1016.3, "visibility": 10, "precipTypeRain": true, "precipTypeNone": false, "icon": "partly-cloudy-night", "sentiment_percent_positive": 0.7341176470588235, "created_at": {"$date": 1510706203000}, "humidity": 0.84, "windSpeed": 9.38, "time": 1510671600, "precipIntensity": 0.0008, "precipProbability": 0.08}, {"precipType": "rain", "cloudCover": 0.42, "precipTypeSnow": false, "timeHour": "2017-11-23 05", "temperature": 55.85, "dewPoint": 53.77, "location": "Seattle", "num_tweets": 22.0, "windBearing": 191, "sentiment_average": 0.2562567640692641, "apparentTemperature": 55.85, "pressure": 1010.51, "visibility": 7.25, "precipTypeRain": true, "precipTypeNone": false, "icon": "partly-cloudy-night", "sentiment_percent_positive": 0.5516528925619835, "created_at": {"$date": 1511431205000}, "humidity": 0.93, "windSpeed": 7.73, "time": 1511442000, "precipIntensity": 0.0089, "precipProbability": 0.26}, {"precipType": "rain", "cloudCover": 0.29, "precipTypeSnow": false, "timeHour": "2017-11-23 06", "temperature": 55.29, "dewPoint": 53.01, "location": "Seattle", "num_tweets": 4.0, "windBearing": 194, "sentiment_average": 0.052500000000000005, "apparentTemperature": 55.29, "pressure": 1010.21, "visibility": 7.16, "precipTypeRain": true, "precipTypeNone": false, "icon": "partly-cloudy-night", "sentiment_percent_positive": 0.4, "created_at": {"$date": 1511434884000}, "humidity": 0.92, "windSpeed": 7.07, "time": 1511445600, "precipIntensity": 0.0073, "precipProbability": 0.24}, {"precipType": "rain", "cloudCover": 0.49, "precipTypeSnow": false, "timeHour": "2017-11-23 07", "temperature": 54.83, "dewPoint": 52.47, "location": "Seattle", "num_tweets": 11.0, "windBearing": 195, "sentiment_average": 0.5600649350649349, "apparentTemperature": 54.83, "pressure": 1009.62, "visibility": 7.07, "precipTypeRain": true, "precipTypeNone": false, "icon": "partly-cloudy-night", "sentiment_percent_positive": 0.9030303030303031, "created_at": {"$date": 1511438805000}, "humidity": 0.92, "windSpeed": 7.04, "time": 1511449200, "precipIntensity": 0.0033, "precipProbability": 0.17}, {"precipType": "rain", "cloudCover": 0.71, "precipTypeSnow": false, "timeHour": "2017-11-23 08", "temperature": 54.37, "dewPoint": 51.95, "location": "Seattle", "num_tweets": 10.0, "windBearing": 201, "sentiment_average": 0.06239583333333334, "apparentTemperature": 54.37, "pressure": 1009.54, "visibility": 5.34, "precipTypeRain": true, "precipTypeNone": false, "icon": "partly-cloudy-day", "sentiment_percent_positive": 0.54375, "created_at": {"$date": 1511442219000}, "humidity": 0.91, "windSpeed": 6.84, "time": 1511452800, "precipIntensity": 0.0097, "precipProbability": 0.56}, {"precipType": "rain", "cloudCover": 0.56, "precipTypeSnow": false, "timeHour": "2017-11-23 09", "temperature": 53.65, "dewPoint": 51.79, "location": "Seattle", "num_tweets": 11.0, "windBearing": 201, "sentiment_average": 0.4795634920634921, "apparentTemperature": 53.65, "pressure": 1009.97, "visibility": 5.76, "precipTypeRain": true, "precipTypeNone": false, "icon": "rain", "sentiment_percent_positive": 0.7418181818181818, "created_at": {"$date": 1511445601000}, "humidity": 0.93, "windSpeed": 7.03, "time": 1511456400, "precipIntensity": 0.0295, "precipProbability": 0.86}, {"precipType": "rain", "cloudCover": 0.71, "precipTypeSnow": false, "timeHour": "2017-11-23 20", "temperature": 54.37, "dewPoint": 51.95, "location": "Seattle", "num_tweets": 99.0, "windBearing": 201, "sentiment_average": 0.43485492020372074, "apparentTemperature": 54.37, "pressure": 1009.54, "visibility": 5.34, "precipTypeRain": true, "precipTypeNone": false, "icon": "partly-cloudy-day", "sentiment_percent_positive": 0.8075757575757576, "created_at": {"$date": 1511485238000}, "humidity": 0.91, "windSpeed": 6.84, "time": 1511452800, "precipIntensity": 0.0097, "precipProbability": 0.56}, {"precipType": "rain", "cloudCover": 0.56, "precipTypeSnow": false, "timeHour": "2017-11-23 21", "temperature": 53.65, "dewPoint": 51.79, "location": "Seattle", "num_tweets": 82.0, "windBearing": 201, "sentiment_average": 0.2588800021117093, "apparentTemperature": 53.65, "pressure": 1009.97, "visibility": 5.76, "precipTypeRain": true, "precipTypeNone": false, "icon": "rain", "sentiment_percent_positive": 0.7092682926829269, "created_at": {"$date": 1511488802000}, "humidity": 0.93, "windSpeed": 7.03, "time": 1511456400, "precipIntensity": 0.0295, "precipProbability": 0.86}, {"precipType": "rain", "cloudCover": 0.11, "precipTypeSnow": false, "timeHour": "2017-11-24 02", "temperature": 47.46, "dewPoint": 43.56, "location": "Seattle", "num_tweets": 72.0, "windBearing": 193, "sentiment_average": 0.21703202661536, "apparentTemperature": 43.41, "pressure": 1016.98, "visibility": 7.33, "precipTypeRain": true, "precipTypeNone": false, "icon": "clear-night", "sentiment_percent_positive": 0.6927083333333334, "created_at": {"$date": 1511506827000}, "humidity": 0.86, "windSpeed": 8.64, "time": 1511517600, "precipIntensity": 0.0003, "precipProbability": 0.04}, {"precipType": "rain", "cloudCover": 0.78, "precipTypeSnow": false, "timeHour": "2017-11-22 18", "temperature": 57.25, "dewPoint": 55.98, "location": "Seattle", "num_tweets": 166.0, "windBearing": 125, "sentiment_average": 0.24080129591236513, "apparentTemperature": 57.25, "pressure": 1014.69, "visibility": 10, "precipTypeRain": true, "precipTypeNone": false, "icon": "partly-cloudy-night", "sentiment_percent_positive": 0.7234939759036149, "created_at": {"$date": 1511391609000}, "humidity": 0.96, "windSpeed": 2.85, "time": 1511359200, "precipIntensity": 0.0007, "precipProbability": 0.13}, {"precipType": "rain", "cloudCover": 0.69, "precipTypeSnow": false, "timeHour": "2017-11-22 19", "temperature": 57.44, "dewPoint": 56.42, "location": "Seattle", "num_tweets": 164.0, "windBearing": 127, "sentiment_average": 0.20556578231502012, "apparentTemperature": 57.44, "pressure": 1014.86, "visibility": 10, "precipTypeRain": true, "precipTypeNone": false, "icon": "partly-cloudy-night", "sentiment_percent_positive": 0.6676829268292681, "created_at": {"$date": 1511395231000}, "humidity": 0.96, "windSpeed": 3.29, "time": 1511362800, "precipIntensity": 0.0025, "precipProbability": 0.31}, {"precipType": "NoPrecip", "cloudCover": 0.55, "precipTypeSnow": false, "timeHour": "2017-11-24 09", "temperature": 47.95, "dewPoint": 42.22, "location": "Seattle", "num_tweets": 26.0, "windBearing": 172, "sentiment_average": 0.36132686757686755, "apparentTemperature": 44.87, "pressure": 1018.77, "visibility": 10, "precipTypeRain": false, "precipTypeNone": true, "icon": "partly-cloudy-day", "sentiment_percent_positive": 0.7369230769230769, "created_at": {"$date": 1511532003000}, "humidity": 0.8, "windSpeed": 6.7, "time": 1511542800, "precipIntensity": 0, "precipProbability": 0}, {"precipType": "rain", "cloudCover": 0.82, "precipTypeSnow": false, "timeHour": "2017-11-24 06", "temperature": 46.79, "dewPoint": 42.58, "location": "Seattle", "num_tweets": 18.0, "windBearing": 178, "sentiment_average": 0.2522193662818663, "apparentTemperature": 42.96, "pressure": 1017.98, "visibility": 7.33, "precipTypeRain": true, "precipTypeNone": false, "icon": "partly-cloudy-night", "sentiment_percent_positive": 0.6666666666666666, "created_at": {"$date": 1511521327000}, "humidity": 0.85, "windSpeed": 7.76, "time": 1511532000, "precipIntensity": 0.0005, "precipProbability": 0.04}, {"precipType": "rain", "cloudCover": 0.26, "precipTypeSnow": false, "timeHour": "2017-11-24 05", "temperature": 46.76, "dewPoint": 42.94, "location": "Seattle", "num_tweets": 14.0, "windBearing": 180, "sentiment_average": 0.13380488559059986, "apparentTemperature": 42.7, "pressure": 1017.97, "visibility": 7.33, "precipTypeRain": true, "precipTypeNone": false, "icon": "partly-cloudy-night", "sentiment_percent_positive": 0.44642857142857145, "created_at": {"$date": 1511517616000}, "humidity": 0.86, "windSpeed": 8.27, "time": 1511528400, "precipIntensity": 0.0001, "precipProbability": 0.01}, {"precipType": "rain", "cloudCover": 0.71, "precipTypeSnow": false, "timeHour": "2017-11-22 11", "temperature": 59.75, "dewPoint": 57.85, "location": "Seattle", "num_tweets": 69.0, "windBearing": 152, "sentiment_average": 0.30744424054206665, "apparentTemperature": 59.82, "pressure": 1015.43, "visibility": 10, "precipTypeRain": true, "precipTypeNone": false, "icon": "partly-cloudy-day", "sentiment_percent_positive": 0.7463768115942029, "created_at": {"$date": 1511368214000}, "humidity": 0.93, "windSpeed": 3, "time": 1511377200, "precipIntensity": 0.0092, "precipProbability": 0.45}, {"precipType": "rain", "cloudCover": 0.67, "precipTypeSnow": false, "timeHour": "2017-11-22 12", "temperature": 61.26, "dewPoint": 58.92, "location": "Seattle", "num_tweets": 1.0, "windBearing": 135, "sentiment_average": 1.0, "apparentTemperature": 61.41, "pressure": 1014.73, "visibility": 10, "precipTypeRain": true, "precipTypeNone": false, "icon": "partly-cloudy-day", "sentiment_percent_positive": 0.3, "created_at": {"$date": 1511370002000}, "humidity": 0.92, "windSpeed": 4.51, "time": 1511380800, "precipIntensity": 0.0048, "precipProbability": 0.36}, {"precipType": "rain", "cloudCover": 0.69, "precipTypeSnow": false, "timeHour": "2017-11-22 13", "temperature": 56.1, "dewPoint": 55.14, "location": "Seattle", "num_tweets": 1.0, "windBearing": 139, "sentiment_average": 0.0, "apparentTemperature": 56.1, "pressure": 1014.13, "visibility": 10, "precipTypeRain": true, "precipTypeNone": false, "icon": "rain", "sentiment_percent_positive": -0.8, "created_at": {"$date": 1511377033000}, "humidity": 0.97, "windSpeed": 3.46, "time": 1511341200, "precipIntensity": 0.03, "precipProbability": 0.86}, {"precipType": "rain", "cloudCover": 0.85, "precipTypeSnow": false, "timeHour": "2017-11-22 14", "temperature": 56.59, "dewPoint": 55.57, "location": "Seattle", "num_tweets": 114.0, "windBearing": 143, "sentiment_average": 0.2727402154375838, "apparentTemperature": 56.59, "pressure": 1014.42, "visibility": 10, "precipTypeRain": true, "precipTypeNone": false, "icon": "partly-cloudy-night", "sentiment_percent_positive": 0.6850877192982456, "created_at": {"$date": 1511377467000}, "humidity": 0.96, "windSpeed": 3.94, "time": 1511344800, "precipIntensity": 0.0207, "precipProbability": 0.77}, {"precipType": "rain", "cloudCover": 0.44, "precipTypeSnow": false, "timeHour": "2017-11-22 15", "temperature": 56.75, "dewPoint": 55.84, "location": "Seattle", "num_tweets": 176.0, "windBearing": 140, "sentiment_average": 0.3009955973339318, "apparentTemperature": 56.75, "pressure": 1014.34, "visibility": 10, "precipTypeRain": true, "precipTypeNone": false, "icon": "partly-cloudy-night", "sentiment_percent_positive": 0.7848863636363638, "created_at": {"$date": 1511380801000}, "humidity": 0.97, "windSpeed": 3.41, "time": 1511348400, "precipIntensity": 0.0233, "precipProbability": 0.86}, {"precipType": "rain", "cloudCover": 0.88, "precipTypeSnow": false, "timeHour": "2017-11-22 16", "temperature": 57.09, "dewPoint": 56.24, "location": "Seattle", "num_tweets": 180.0, "windBearing": 150, "sentiment_average": 0.2939440223164182, "apparentTemperature": 57.09, "pressure": 1014.3, "visibility": 10, "precipTypeRain": true, "precipTypeNone": false, "icon": "partly-cloudy-night", "sentiment_percent_positive": 0.7583333333333333, "created_at": {"$date": 1511384408000}, "humidity": 0.97, "windSpeed": 2.61, "time": 1511352000, "precipIntensity": 0.0095, "precipProbability": 0.41}, {"precipType": "rain", "cloudCover": 0.9, "precipTypeSnow": false, "timeHour": "2017-11-22 17", "temperature": 57.22, "dewPoint": 56.3, "location": "Seattle", "num_tweets": 136.0, "windBearing": 122, "sentiment_average": 0.27236912631214116, "apparentTemperature": 57.22, "pressure": 1014.59, "visibility": 10, "precipTypeRain": true, "precipTypeNone": false, "icon": "partly-cloudy-night", "sentiment_percent_positive": 0.809436274509804, "created_at": {"$date": 1511388022000}, "humidity": 0.97, "windSpeed": 3.15, "time": 1511355600, "precipIntensity": 0.0061, "precipProbability": 0.35}, {"precipType": "rain", "cloudCover": 0.12, "precipTypeSnow": false, "timeHour": "2017-11-24 15", "temperature": 47.3, "dewPoint": 43.18, "location": "Seattle", "num_tweets": 137.0, "windBearing": 193, "sentiment_average": 0.25720959595959614, "apparentTemperature": 43.37, "pressure": 1017.55, "visibility": 7.33, "precipTypeRain": true, "precipTypeNone": false, "icon": "clear-night", "sentiment_percent_positive": 0.7382481751824816, "created_at": {"$date": 1511553603000}, "humidity": 0.86, "windSpeed": 8.27, "time": 1511521200, "precipIntensity": 0.0003, "precipProbability": 0.04}, {"precipType": "rain", "cloudCover": 0.64, "precipTypeSnow": false, "timeHour": "2017-11-24 11", "temperature": 50.15, "dewPoint": 42.17, "location": "Seattle", "num_tweets": 130.0, "windBearing": 182, "sentiment_average": 0.2124494856994858, "apparentTemperature": 50.15, "pressure": 1019.04, "visibility": 10, "precipTypeRain": true, "precipTypeNone": false, "icon": "partly-cloudy-day", "sentiment_percent_positive": 0.6576923076923079, "created_at": {"$date": 1511539250000}, "humidity": 0.74, "windSpeed": 8.45, "time": 1511550000, "precipIntensity": 0.0001, "precipProbability": 0.01}, {"precipType": "rain", "cloudCover": 0.44, "precipTypeSnow": false, "timeHour": "2017-11-24 00", "temperature": 50.9, "dewPoint": 42.4, "location": "Seattle", "num_tweets": 91.0, "windBearing": 175, "sentiment_average": 0.32504250976435034, "apparentTemperature": 50.9, "pressure": 1019.01, "visibility": 7.33, "precipTypeRain": true, "precipTypeNone": false, "icon": "partly-cloudy-day", "sentiment_percent_positive": 0.7461538461538462, "created_at": {"$date": 1511499604000}, "humidity": 0.73, "windSpeed": 8.11, "time": 1511553600, "precipIntensity": 0.0005, "precipProbability": 0.06}, {"precipType": "rain", "cloudCover": 0.3, "precipTypeSnow": false, "timeHour": "2017-11-24 04", "temperature": 46.9, "dewPoint": 43.05, "location": "Seattle", "num_tweets": 39.0, "windBearing": 182, "sentiment_average": 0.27480497897164563, "apparentTemperature": 42.68, "pressure": 1017.69, "visibility": 7.3, "precipTypeRain": true, "precipTypeNone": false, "icon": "partly-cloudy-night", "sentiment_percent_positive": 0.7282051282051281, "created_at": {"$date": 1511514043000}, "humidity": 0.86, "windSpeed": 8.72, "time": 1511524800, "precipIntensity": 0.0005, "precipProbability": 0.06}, {"precipType": "rain", "cloudCover": 0.7, "precipTypeSnow": false, "timeHour": "2017-11-23 04", "temperature": 55.89, "dewPoint": 53.92, "location": "Seattle", "num_tweets": 30.0, "windBearing": 188, "sentiment_average": 0.494555114638448, "apparentTemperature": 55.89, "pressure": 1011.1, "visibility": 7.33, "precipTypeRain": true, "precipTypeNone": false, "icon": "partly-cloudy-night", "sentiment_percent_positive": 0.8291666666666667, "created_at": {"$date": 1511427689000}, "humidity": 0.93, "windSpeed": 7.67, "time": 1511438400, "precipIntensity": 0.0013, "precipProbability": 0.06}, {"precipType": "rain", "cloudCover": 0.68, "precipTypeSnow": false, "timeHour": "2017-11-24 07", "temperature": 46.67, "dewPoint": 42.06, "location": "Seattle", "num_tweets": 7.0, "windBearing": 181, "sentiment_average": 0.35034013605442177, "apparentTemperature": 43.05, "pressure": 1018.15, "visibility": 8.49, "precipTypeRain": true, "precipTypeNone": false, "icon": "partly-cloudy-night", "sentiment_percent_positive": 0.7071428571428572, "created_at": {"$date": 1511524918000}, "humidity": 0.84, "windSpeed": 7.28, "time": 1511535600, "precipIntensity": 0.0001, "precipProbability": 0.01}, {"precipType": "rain", "cloudCover": 0.42, "precipTypeSnow": false, "timeHour": "2017-11-23 17", "temperature": 55.85, "dewPoint": 53.77, "location": "Seattle", "num_tweets": 150.0, "windBearing": 191, "sentiment_average": 0.306616296897547, "apparentTemperature": 55.85, "pressure": 1010.51, "visibility": 7.25, "precipTypeRain": true, "precipTypeNone": false, "icon": "partly-cloudy-night", "sentiment_percent_positive": 0.7380000000000001, "created_at": {"$date": 1511474404000}, "humidity": 0.93, "windSpeed": 7.73, "time": 1511442000, "precipIntensity": 0.0089, "precipProbability": 0.26}, {"precipType": "rain", "cloudCover": 0.7, "precipTypeSnow": false, "timeHour": "2017-11-23 16", "temperature": 55.89, "dewPoint": 53.92, "location": "Seattle", "num_tweets": 137.0, "windBearing": 188, "sentiment_average": 0.3295625764729322, "apparentTemperature": 55.89, "pressure": 1011.1, "visibility": 7.33, "precipTypeRain": true, "precipTypeNone": false, "icon": "partly-cloudy-night", "sentiment_percent_positive": 0.7357664233576641, "created_at": {"$date": 1511470803000}, "humidity": 0.93, "windSpeed": 7.67, "time": 1511438400, "precipIntensity": 0.0013, "precipProbability": 0.06}, {"precipType": "rain", "cloudCover": 0.54, "precipTypeSnow": false, "timeHour": "2017-11-23 15", "temperature": 56.42, "dewPoint": 54.41, "location": "Seattle", "num_tweets": 158.0, "windBearing": 188, "sentiment_average": 0.3499149111480996, "apparentTemperature": 56.42, "pressure": 1011.7, "visibility": 7.33, "precipTypeRain": true, "precipTypeNone": false, "icon": "partly-cloudy-night", "sentiment_percent_positive": 0.7908227848101265, "created_at": {"$date": 1511467200000}, "humidity": 0.93, "windSpeed": 8.7, "time": 1511434800, "precipIntensity": 0.0017, "precipProbability": 0.16}, {"precipType": "rain", "cloudCover": 0.61, "precipTypeSnow": false, "timeHour": "2017-11-23 14", "temperature": 56.89, "dewPoint": 54.97, "location": "Seattle", "num_tweets": 171.0, "windBearing": 191, "sentiment_average": 0.4148334852282222, "apparentTemperature": 56.89, "pressure": 1011.27, "visibility": 7.31, "precipTypeRain": true, "precipTypeNone": false, "icon": "partly-cloudy-night", "sentiment_percent_positive": 0.8121345029239766, "created_at": {"$date": 1511463618000}, "humidity": 0.93, "windSpeed": 8.58, "time": 1511431200, "precipIntensity": 0.0095, "precipProbability": 0.52}, {"precipType": "rain", "cloudCover": 0.31, "precipTypeSnow": false, "timeHour": "2017-11-14 20", "temperature": 47.37, "dewPoint": 41.13, "location": "Seattle", "num_tweets": 16.0, "windBearing": 130, "sentiment_average": 0.4542162698412699, "apparentTemperature": 42.92, "pressure": 1016.32, "visibility": 9.92, "precipTypeRain": true, "precipTypeNone": false, "icon": "partly-cloudy-day", "sentiment_percent_positive": 0.7937500000000001, "created_at": {"$date": 1510707609000}, "humidity": 0.79, "windSpeed": 9.63, "time": 1510675200, "precipIntensity": 0.0008, "precipProbability": 0.08}, {"precipType": "rain", "cloudCover": 0.62, "precipTypeSnow": false, "timeHour": "2017-11-23 12", "temperature": 52.22, "dewPoint": 50.35, "location": "Seattle", "num_tweets": 42.0, "windBearing": 231, "sentiment_average": 0.45405944364277717, "apparentTemperature": 52.22, "pressure": 1010.33, "visibility": 7.08, "precipTypeRain": true, "precipTypeNone": false, "icon": "partly-cloudy-day", "sentiment_percent_positive": 0.8452380952380952, "created_at": {"$date": 1511459042000}, "humidity": 0.93, "windSpeed": 3.32, "time": 1511467200, "precipIntensity": 0.0187, "precipProbability": 0.71}, {"precipType": "rain", "cloudCover": 0.64, "precipTypeSnow": false, "timeHour": "2017-11-23 11", "temperature": 53.02, "dewPoint": 51.08, "location": "Seattle", "num_tweets": 9.0, "windBearing": 216, "sentiment_average": 0.25833333333333336, "apparentTemperature": 53.02, "pressure": 1010, "visibility": 6.38, "precipTypeRain": true, "precipTypeNone": false, "icon": "partly-cloudy-day", "sentiment_percent_positive": 0.4666666666666667, "created_at": {"$date": 1511452813000}, "humidity": 0.93, "windSpeed": 2.36, "time": 1511463600, "precipIntensity": 0.0185, "precipProbability": 0.5}, {"precipType": "rain", "cloudCover": 0.8, "precipTypeSnow": false, "timeHour": "2017-11-23 10", "temperature": 53.37, "dewPoint": 51.59, "location": "Seattle", "num_tweets": 51.0, "windBearing": 206, "sentiment_average": 0.5113611606258667, "apparentTemperature": 53.37, "pressure": 1009.87, "visibility": 6.32, "precipTypeRain": true, "precipTypeNone": false, "icon": "partly-cloudy-day", "sentiment_percent_positive": 0.9117647058823529, "created_at": {"$date": 1511449440000}, "humidity": 0.94, "windSpeed": 4.56, "time": 1511460000, "precipIntensity": 0.0237, "precipProbability": 0.78}, {"precipType": "rain", "cloudCover": 0.2, "precipTypeSnow": false, "timeHour": "2017-11-24 01", "temperature": 47.76, "dewPoint": 44.36, "location": "Seattle", "num_tweets": 77.0, "windBearing": 191, "sentiment_average": 0.23670456887989355, "apparentTemperature": 43.62, "pressure": 1016.43, "visibility": 7.33, "precipTypeRain": true, "precipTypeNone": false, "icon": "clear-night", "sentiment_percent_positive": 0.664935064935065, "created_at": {"$date": 1511503361000}, "humidity": 0.88, "windSpeed": 9.03, "time": 1511514000, "precipIntensity": 0.0011, "precipProbability": 0.1}, {"precipType": "rain", "cloudCover": 0.49, "precipTypeSnow": false, "timeHour": "2017-11-23 19", "temperature": 54.83, "dewPoint": 52.47, "location": "Seattle", "num_tweets": 98.0, "windBearing": 195, "sentiment_average": 0.4242770268280472, "apparentTemperature": 54.83, "pressure": 1009.62, "visibility": 7.07, "precipTypeRain": true, "precipTypeNone": false, "icon": "partly-cloudy-night", "sentiment_percent_positive": 0.8177179962894248, "created_at": {"$date": 1511481602000}, "humidity": 0.92, "windSpeed": 7.04, "time": 1511449200, "precipIntensity": 0.0033, "precipProbability": 0.17}, {"precipType": "rain", "cloudCover": 0.29, "precipTypeSnow": false, "timeHour": "2017-11-23 18", "temperature": 55.29, "dewPoint": 53.01, "location": "Seattle", "num_tweets": 119.0, "windBearing": 194, "sentiment_average": 0.3826244487694069, "apparentTemperature": 55.29, "pressure": 1010.21, "visibility": 7.16, "precipTypeRain": true, "precipTypeNone": false, "icon": "partly-cloudy-night", "sentiment_percent_positive": 0.7899159663865546, "created_at": {"$date": 1511478153000}, "humidity": 0.92, "windSpeed": 7.07, "time": 1511445600, "precipIntensity": 0.0073, "precipProbability": 0.24}, {"precipType": "rain", "cloudCover": 0.92, "precipTypeSnow": false, "timeHour": "2017-11-21 18", "temperature": 42.17, "dewPoint": 40.31, "location": "Seattle", "num_tweets": 102.0, "windBearing": 336, "sentiment_average": 0.22039138466834549, "apparentTemperature": 42.17, "pressure": 1015.8, "visibility": 10, "precipTypeRain": true, "precipTypeNone": false, "icon": "rain", "sentiment_percent_positive": 0.7046568627450983, "created_at": {"$date": 1511305229000}, "humidity": 0.93, "windSpeed": 1.48, "time": 1511272800, "precipIntensity": 0.0291, "precipProbability": 0.89}, {"precipType": "rain", "cloudCover": 0.12, "precipTypeSnow": false, "timeHour": "2017-11-24 03", "temperature": 47.3, "dewPoint": 43.18, "location": "Seattle", "num_tweets": 46.0, "windBearing": 193, "sentiment_average": 0.28002850712089844, "apparentTemperature": 43.37, "pressure": 1017.55, "visibility": 7.33, "precipTypeRain": true, "precipTypeNone": false, "icon": "clear-night", "sentiment_percent_positive": 0.70012077294686, "created_at": {"$date": 1511510457000}, "humidity": 0.86, "windSpeed": 8.27, "time": 1511521200, "precipIntensity": 0.0003, "precipProbability": 0.04}, {"precipType": "rain", "cloudCover": 0.64, "precipTypeSnow": false, "timeHour": "2017-11-23 23", "temperature": 53.02, "dewPoint": 51.08, "location": "Seattle", "num_tweets": 86.0, "windBearing": 216, "sentiment_average": 0.2513441572961923, "apparentTemperature": 53.02, "pressure": 1010, "visibility": 6.38, "precipTypeRain": true, "precipTypeNone": false, "icon": "partly-cloudy-day", "sentiment_percent_positive": 0.751453488372093, "created_at": {"$date": 1511496020000}, "humidity": 0.93, "windSpeed": 2.36, "time": 1511463600, "precipIntensity": 0.0185, "precipProbability": 0.5}, {"precipType": "rain", "cloudCover": 0.3, "precipTypeSnow": false, "timeHour": "2017-11-24 16", "temperature": 46.9, "dewPoint": 43.05, "location": "Seattle", "num_tweets": 46.0, "windBearing": 182, "sentiment_average": 0.296183300395257, "apparentTemperature": 42.68, "pressure": 1017.69, "visibility": 7.3, "precipTypeRain": true, "precipTypeNone": false, "icon": "partly-cloudy-night", "sentiment_percent_positive": 0.7445652173913043, "created_at": {"$date": 1511557207000}, "humidity": 0.86, "windSpeed": 8.72, "time": 1511524800, "precipIntensity": 0.0005, "precipProbability": 0.06}, {"precipType": "rain", "cloudCover": 0.26, "precipTypeSnow": false, "timeHour": "2017-11-24 17", "temperature": 46.76, "dewPoint": 42.94, "location": "Seattle", "num_tweets": 4.0, "windBearing": 180, "sentiment_average": 0.5208333333333334, "apparentTemperature": 42.7, "pressure": 1017.97, "visibility": 7.33, "precipTypeRain": true, "precipTypeNone": false, "icon": "partly-cloudy-night", "sentiment_percent_positive": 0.5390625, "created_at": {"$date": 1511560912000}, "humidity": 0.86, "windSpeed": 8.27, "time": 1511528400, "precipIntensity": 0.0001, "precipProbability": 0.01}, {"precipType": "rain", "cloudCover": 0.11, "precipTypeSnow": false, "timeHour": "2017-11-24 14", "temperature": 47.46, "dewPoint": 43.56, "location": "Seattle", "num_tweets": 139.0, "windBearing": 193, "sentiment_average": 0.2842463366968763, "apparentTemperature": 43.41, "pressure": 1016.98, "visibility": 7.33, "precipTypeRain": true, "precipTypeNone": false, "icon": "clear-night", "sentiment_percent_positive": 0.7072841726618705, "created_at": {"$date": 1511550014000}, "humidity": 0.86, "windSpeed": 8.64, "time": 1511517600, "precipIntensity": 0.0003, "precipProbability": 0.04}, {"precipType": "rain", "cloudCover": 0.44, "precipTypeSnow": false, "timeHour": "2017-11-21 12", "temperature": 45.28, "dewPoint": 44.33, "location": "Seattle", "num_tweets": 26.0, "windBearing": 314, "sentiment_average": 0.18050595238095232, "apparentTemperature": 45.28, "pressure": 1012.88, "visibility": 10, "precipTypeRain": true, "precipTypeNone": false, "icon": "rain", "sentiment_percent_positive": 0.6975524475524476, "created_at": {"$date": 1511284828000}, "humidity": 0.96, "windSpeed": 2.12, "time": 1511294400, "precipIntensity": 0.0691, "precipProbability": 0.9}, {"precipType": "rain", "cloudCover": 0.44, "precipTypeSnow": false, "timeHour": "2017-11-24 12", "temperature": 50.9, "dewPoint": 42.4, "location": "Seattle", "num_tweets": 142.0, "windBearing": 175, "sentiment_average": 0.2224419877852975, "apparentTemperature": 50.9, "pressure": 1019.01, "visibility": 7.33, "precipTypeRain": true, "precipTypeNone": false, "icon": "partly-cloudy-day", "sentiment_percent_positive": 0.6699992886612605, "created_at": {"$date": 1511542812000}, "humidity": 0.73, "windSpeed": 8.11, "time": 1511553600, "precipIntensity": 0.0005, "precipProbability": 0.06}, {"precipType": "rain", "cloudCover": 0.2, "precipTypeSnow": false, "timeHour": "2017-11-24 13", "temperature": 47.76, "dewPoint": 44.36, "location": "Seattle", "num_tweets": 130.0, "windBearing": 191, "sentiment_average": 0.26849747127872153, "apparentTemperature": 43.62, "pressure": 1016.43, "visibility": 7.33, "precipTypeRain": true, "precipTypeNone": false, "icon": "clear-night", "sentiment_percent_positive": 0.7365384615384616, "created_at": {"$date": 1511546413000}, "humidity": 0.88, "windSpeed": 9.03, "time": 1511514000, "precipIntensity": 0.0011, "precipProbability": 0.1}, {"precipType": "rain", "cloudCover": 0.75, "precipTypeSnow": false, "timeHour": "2017-11-21 17", "temperature": 41.38, "dewPoint": 39.31, "location": "Seattle", "num_tweets": 76.0, "windBearing": 155, "sentiment_average": 0.2361902467659047, "apparentTemperature": 41.38, "pressure": 1015.82, "visibility": 10, "precipTypeRain": true, "precipTypeNone": false, "icon": "partly-cloudy-night", "sentiment_percent_positive": 0.6934210526315789, "created_at": {"$date": 1511303244000}, "humidity": 0.92, "windSpeed": 0.34, "time": 1511269200, "precipIntensity": 0.0073, "precipProbability": 0.57}, {"precipType": "rain", "cloudCover": 0.8, "precipTypeSnow": false, "timeHour": "2017-11-21 16", "temperature": 40.95, "dewPoint": 39.01, "location": "Seattle", "num_tweets": 91.0, "windBearing": 103, "sentiment_average": 0.2065035823964396, "apparentTemperature": 40.95, "pressure": 1016.49, "visibility": 10, "precipTypeRain": true, "precipTypeNone": false, "icon": "partly-cloudy-night", "sentiment_percent_positive": 0.7197802197802198, "created_at": {"$date": 1511299120000}, "humidity": 0.93, "windSpeed": 0.52, "time": 1511265600, "precipIntensity": 0.0007, "precipProbability": 0.05}]